[
  {
    "model": "catalog.category",
    "pk": 1,
    "fields": {
      "name": "мальчики",
      "description": "Включает в себя машины, автоматы, роботы и др."
    }
  },
  {
    "model": "catalog.category",
    "pk": 2,
    "fields": {
      "name": "девочки",
      "description": "Включаетв себя кукол, дома и мебель для кукол, детскую косметику и мягкие игрушки"
    }
  },
  {
    "model": "catalog.category",
    "pk": 3,
    "fields": {
      "name": "Настольно-печатные игры",
      "description": "Включает в себя настольные игры"
    }
  },
  {
    "model": "catalog.product",
    "pk": 1,
    "fields": {
      "name": "Автомат",
      "description": "Обладает световым и звуковым эффектом. Работает от трех элементов питания типа АА",
      "image": "",
      "category_product": 1,
      "price": "200.00",
      "date_of_creation": "2023-09-24",
      "last_modified_date": "2023-09-24"
    }
  },
  {
    "model": "catalog.product",
    "pk": 2,
    "fields": {
      "name": "Машина на р/у",
      "description": "Игрушка подходит для игры на улице в сухую погоду. В комплекте аккумулятор для машины и зарядное устройство",
      "image": "",
      "category_product": 1,
      "price": "150.00",
      "date_of_creation": "2023-09-24",
      "last_modified_date": "2023-09-24"
    }
  },
  {
    "model": "catalog.product",
    "pk": 3,
    "fields": {
      "name": "Дом для кукол",
      "description": "Размеры в собранном виде(Д*Ш*В): 700*350*850 мм, в комплекте: мебель для гостиной, в дома есть лифт",
      "image": "",
      "category_product": 2,
      "price": "600.00",
      "date_of_creation": "2023-09-24",
      "last_modified_date": "2023-09-24"
    }
  },
  {
    "model": "catalog.product",
    "pk": 4,
    "fields": {
      "name": "Кукла Barby Extra",
      "description": "Высота куклы 30см, в комплекте: аксессуары, домашний питомец(1 шт), одежда",
      "image": "",
      "category_product": 2,
      "price": "250.00",
      "date_of_creation": "2023-09-24",
      "last_modified_date": "2023-09-24"
    }
  },
  {
    "model": "catalog.product",
    "pk": 5,
    "fields": {
      "name": "Настольная игра \"Anno 1800\"",
      "description": "Рекомендуемый возраст: 14+, Игроков: от 2 до 4, Время игры: ~120 мин",
      "image": "",
      "category_product": 3,
      "price": "400.00",
      "date_of_creation": "2023-09-24",
      "last_modified_date": "2023-09-24"
    }
  }
]